dn3/__init__.py
dn3/crypto/__init__.py
dn3/crypto/primitives.py
dn3/l1ght/__init__.py
dn3/l1ght/context.py
dn3/l1ght/elf.py
dn3/l1ght/gdb.py
dn3/l1ght/pipe.py
dn3/l1ght/proc.py
dn3/l1ght/sock.py
dn3/misc/__init__.py
dn3/misc/colors.py
dn3/misc/encoding.py
dn3/misc/utils.py
dn3/pwn/__init__.py
dn3/pwn/cyclic.py
dn3/pwn/deathnot3.py
dn3/pwn/fmtstr.py
dn3/tools/__init__.py
dn3/tools/cli.py
dn3/tools/config.py
dn3/tools/linkerpatcher.py
dn3/tools/templategen.py
dn3-1.2.1.dist-info/LICENSE
dn3-1.2.1.dist-info/METADATA
dn3-1.2.1.dist-info/WHEEL
dn3-1.2.1.dist-info/entry_points.txt
dn3-1.2.1.dist-info/top_level.txt
dn3-1.2.1.dist-info/RECORD
