Metadata-Version: 2.1
Name: dn3
Version: 1.2.1
Home-page: https://github.com/k1R4/deathnot3/
Author: k1R4
Author-email: srijiith@outlook.com
Keywords: pwn
Classifier: Programming Language :: Python :: 3
Classifier: License :: OSI Approved :: MIT License
Requires-Python: >=3.6, <4
License-File: LICENSE
Requires-Dist: pyelftools
Requires-Dist: zstandard
Requires-Dist: unix-ar
Requires-Dist: wget
Requires-Dist: requests
